{
    "fluentMethods": true,
    "clientRootFolder": "",
    "relationships": [],
    "fields": [
        {
            "fieldName": "description",
            "fieldType": "String",
            "fieldValidateRules": [
                "maxlength"
            ],
            "fieldValidateRulesMaxlength": "200"
        },
        {
            "fieldName": "createdBy",
            "fieldType": "String",
            "fieldValidateRules": [
                "maxlength"
            ],
            "fieldValidateRulesMaxlength": "50"
        },
        {
            "fieldName": "createdDate",
            "fieldType": "Instant"
        },
        {
            "fieldName": "lastUpdatedBy",
            "fieldType": "String",
            "fieldValidateRules": [
                "maxlength"
            ],
            "fieldValidateRulesMaxlength": "50"
        },
        {
            "fieldName": "lastUpdatedDate",
            "fieldType": "Instant"
        }
    ],
    "changelogDate": "20190222035044",
    "dto": "no",
    "searchEngine": false,
    "service": "no",
    "entityTableName": "policies_group",
    "jpaMetamodelFiltering": false,
    "pagination": "pagination"
}
